xkernel/__init__.py
xkernel/__main__.py
xkernel/bundle.py
xkernel/cli.py
xkernel/demo_einstein.py
xkernel/demo_schrodinger.py
xkernel/demo_shannon.py
xkernel/engine.py
xkernel/fiber.py
xkernel/filament.py
xkernel/lens_einstein.py
xkernel/lens_schrodinger.py
xkernel/lens_shannon.py
xkernel/lens_wave.py
xkernel/viewer_bounce_dot.py
xkernel/xkernel.py
xkernel-0.0.1.dist-info/licenses/LICENSE
xkernel-0.0.1.dist-info/METADATA
xkernel-0.0.1.dist-info/WHEEL
xkernel-0.0.1.dist-info/entry_points.txt
xkernel-0.0.1.dist-info/top_level.txt
xkernel-0.0.1.dist-info/RECORD
