Metadata-Version: 2.4
Name: xkernel
Version: 0.0.1
Summary: Minimal deterministic X-kernel with filament, fiber, and bundle structures.
Author: Scott Allen Cave
License: MIT
Project-URL: Homepage, https://github.com/xkernelorg/xkernel
Project-URL: Issues, https://github.com/xkernelorg/xkernel/issues
Classifier: Programming Language :: Python :: 3
Classifier: Programming Language :: Python :: 3.12
Classifier: License :: OSI Approved :: MIT License
Classifier: Operating System :: OS Independent
Requires-Python: >=3.12
License-File: LICENSE
Requires-Dist: b32k>=0.0.2
Dynamic: license-file
